isometric/__init__.py
isometric/_vectors.py
isometric-1.3.5.dist-info/LICENSE.txt
isometric-1.3.5.dist-info/METADATA
isometric-1.3.5.dist-info/WHEEL
isometric-1.3.5.dist-info/top_level.txt
isometric-1.3.5.dist-info/RECORD
