Metadata-Version: 2.1
Name: isometric
Version: 1.3.5
Summary: Vectors on an isometric grid.
Author-email: Johannes <johannes-programming@posteo.org>
License: The MIT License (MIT)
Classifier: License :: OSI Approved :: MIT License
Classifier: Programming Language :: Python
Classifier: Programming Language :: Python :: 3
Requires-Python: >=3.11
License-File: LICENSE.txt
